{
  "logo": {
    "alt": "Glamour logo by deco",
    "src": "https://ozksgdmyrqcxcwhnbepg.supabase.co/storage/v1/object/public/assets/10646/62d6b505-2f79-4192-8e14-90dda1e99a5d",
    "width": 180,
    "height": 26
  },
  "alerts": [],
  "navItems": {
    "__resolveType": "navbar"
  },
  "__resolveType": "site/sections/Header/Header.tsx",
  "searchbar": {
    "placeholder": "What are you looking for?",
    "loader": {
      "data": {
        "searches": [],
        "products": [],
        "__resolveType": "vtex/loaders/intelligentSearch/suggestions.ts",
        "count": 6
      },
      "__resolveType": "resolved"
    }
  },
  "mode": "private",
  "alert": {
    "alerts": [
      {
        "title": "1ª DEVOLUÇÃO GRÁTIS\"",
        "description": "Seu produto não era o que esperava?Solicite a troca através do e-mail atendimento@bagaggio.com.br ou no nosso chat. De segunda à sexta, das 09 às 18h"
      },
      {
        "title": "COMPRE PELO WHATSAPP",
        "description": "Entre em contato com uma de nossas lojas e compre pelo Whatsapp"
      },
      {
        "title": "10% OFF NA SUA PRIMEIRA COMPRA",
        "description": "Use o cupom SOUBAGAGGIO e garanta 10% de desconto na sua primeira compra. *desconto não cumulativo com outras promoções do site",
        "activeForm": true
      },
      {
        "title": "TROQUE FÁCIL",
        "description": "Para solicitar a troca, devolução ou uso da garantia acesse o link [**Troque Fácil**](https://bagaggio.troquefacil.com.br/) apresente o número do pedido e o CPF vinculado a compra. Em seguida, selecione o produto e o motivo da solicitação"
      },
      {
        "title": "PARA EMPRESAS",
        "description": "Atendimento exclusivo para empresas, por telefone, e-mail e whatsapp. Solicite seu orçamento."
      }
    ],
    "backgroundColor": "#0274BB",
    "interval": 50
  }
}